network2tikz/__about__.py
network2tikz/__init__.py
network2tikz/canvas.py
network2tikz/drawing.py
network2tikz/exceptions.py
network2tikz/layout.py
network2tikz/plot.py
network2tikz/units.py
network2tikz-0.1.8.dist-info/METADATA
network2tikz-0.1.8.dist-info/RECORD
network2tikz-0.1.8.dist-info/WHEEL
network2tikz-0.1.8.dist-info/top_level.txt
