Metadata-Version: 2.1
Name: network2tikz
Version: 0.1.8
Summary: A converter that takes a network (cnet, igraph, networkx, pathpy, ...) and creates a tikz-network for smooth integration into LaTeX.
Home-page: https://github.com/hackl/network2tikz
Author: Juergen Hackl
Author-email: hackl.j@gmx.at
License: License :: OSI Approved :: GNU General Public License v3 (GPLv3)
Download-URL: https://pypi.org/project/network2tikz
Platform: UNKNOWN
Classifier: Development Status :: 4 - Beta
Classifier: License :: OSI Approved :: GNU General Public License v3 (GPLv3)
Classifier: Operating System :: OS Independent
Classifier: Programming Language :: Python
Classifier: Programming Language :: Python :: 3
Classifier: Intended Audience :: Science/Research
Classifier: Topic :: Multimedia :: Graphics :: Graphics Conversion
Classifier: Topic :: Scientific/Engineering :: Visualization
